Workbook

Sheet 项目概览
A1: 研报文本自动生成PPT项目 — 本科生实习项目计划
A3: 项目名称 | B3: 研报文本 → 可视化PowerPoint 自动生成系统
A4: 项目目标 | B4: 输入：一家上市公司研报的纯文本（可能含markdown格式）。输出：一份结构清晰、风格统一的PowerPoint文件，除保留研报原有信息外，对文本中可被可视化的数值信息（如营收/利润趋势、增长率、估值对比等）自动定位并调用可视化工具生成图表或表格嵌入对应幻灯片。
A5: 参考项目 | B5: MemSlides（https://github.com/huohua325/Memslides）：分层记忆驱动的个性化PPT生成Agent框架，输入为论文PDF，通过 generate / revise / template-induct 三段式流程生成用户风格感知的slides。可复用其 template induction（模板归纳）与 python-pptx 渲染思路。
A6: 与MemSlides的关键差异（重点） | B6: ① 风格：本项目不做用户个性化风格记忆，只需支持一套给定的固定模板/风格，可大幅简化MemSlides的分层记忆(用户画像记忆)设计。 ② 输入内容：本项目的研报是纯文本叙述，不含现成图片/图表/表格，需要新增“可视化内容定位”能力——从文本中识别可被图表化的数值信息，抽取结构化数据，再调用可视化工具生成图片/表格后嵌入。这是MemSlides没有的模块。
A7: 团队人员 | B7: 2名本科生实习生（记为 学生A、学生B），可结对讨论、共同解决问题；模块所有权按方向划分，每周集成同步
A8: 学生A 主要方向 | B8: 文本解析与内容理解：markdown/文本解析、幻灯片大纲生成、可视化内容定位与结构化数据抽取
A9: 学生B 主要方向 | B9: 可视化与排版：图表/表格渲染、固定模板与版式引擎、PPT组装与样式统一
A10: 项目周期 | B10: 核心任务按4周详细排期（见“任务跟踪表”）；总时长不超过8周——若个别任务在第4周末仍未完成，直接在任务跟踪表中把该行“计划周次”改为5/6/7/8继续跟踪即可，第5-8周不预先安排具体任务，按需顺延
A11: 项目启动日期（可修改） | B11: 2026-07-06
A12: 技术栈建议 | B12: Python、python-pptx、matplotlib/plotly（图表渲染）、pandas（结构化数据）、Claude/LLM API（大纲生成与信息抽取）、pytest（测试）、Git（版本管理）
A13: 协作方式 | B13: 每周1次导师同步会；学生每日/隔日异步同步进度；每周五更新本Excel“任务跟踪表”状态；遇阻塞问题先结对讨论30分钟，无法解决再上报导师
A14: 最终交付物 | B14: 1) 端到端代码仓库（含README与环境搭建说明） 2) 支持固定模板的研报文本→PPT生成pipeline 3) 测试报告（抽取准确率、生成成功率等） 4) 项目总结文档 5) 结项汇报PPT
A19: 第1周（18h）：环境搭建、MemSlides调研、样例数据与模板准备
A20: 第2周（27h）：文本解析、大纲生成、基础排版引擎、首个端到端小demo
A21: 第3周（31h）：数值定位抽取、图表/表格渲染、首次全流程打通
A22: 第4周（30h）：排版打磨、全量测试、精简单元测试+评估报告、文档与结项汇报

Sheet 系统架构设计
A1: 阶段 | B1: 模块 | C1: 输入 | D1: 输出 | E1: 关键技术/工具 | F1: 与MemSlides的对应/差异
A2: 1 | B2: 文本/Markdown解析 | C2: 研报纯文本(含markdown) | D2: 结构化文档树(标题层级/段落/列表/已有表格) | E2: 正则+markdown解析库(如mistune/python-markdown) | F2: MemSlides处理PDF论文结构；本项目处理纯文本/markdown结构，更轻量
A3: 2 | B3: 幻灯片大纲生成 | C3: 结构化文档树 | D3: 大纲JSON(章节->幻灯片标题+要点+原文引用) | E3: LLM(Claude) few-shot 摘要与切分 | F3: 对应MemSlides的内容规划阶段，但不含用户画像个性化
A4: 3 | B4: 可视化内容定位与抽取 | C4: 文档正文段落 | D4: 结构化数据JSON{图表类型,标题,单位,分类,数值,来源片段} | E4: 关键词/正则初筛 + LLM结构化抽取 + 数值核对 | F4: MemSlides输入本身含图表，无需此模块；这是本项目新增的核心模块
A5: 4 | B5: 可视化渲染 | C5: 结构化数据JSON | D5: 图表图片(bar/line/pie)或PPT原生表格 | E5: matplotlib/plotly、python-pptx表格API | F5: 新增模块，风格需与固定模板配色统一
A6: 5 | B6: 模板与版式引擎 | C6: 固定PPT模板 + 内容类型(文字/图表/表格/混排) | D6: 版式选择结果(layout映射) | E6: python-pptx读取母版占位符；参考MemSlides template induct思路简化为“固定模板”版本 | F6: MemSlides做用户风格个性化归纳；本项目只需归纳1套固定模板的可复用版式
A7: 6 | B7: PPT组装 | C7: 大纲JSON + 图表/表格 + 版式映射 | D7: 完整.pptx文件 | E7: python-pptx | F7: 对应MemSlides最终渲染输出环节
A8: 7(可选/进阶) | B8: 局部修订 | C8: 用户对某页的修改反馈 | D8: 仅重新生成受影响的幻灯片 | E8: 借鉴MemSlides的scoped local revision思路 | F8: MemSlides核心创新点之一，本项目作为进阶/加分项，非必须

Sheet 任务跟踪表
A1: 任务ID | B1: 计划周次 | C1: 模块 | D1: 任务描述 | E1: 负责人 | F1: 协作人 | G1: 优先级 | H1: 预计工时(h) | I1: 前置任务 | J1: 交付物/验收标准(DoD) | K1: 状态 | L1: 计划开始日期 | M1: 计划完成日期 | N1: 实际完成日期 | O1: 备注
A2: T1.1 | B2: 1 | C2: 前期准备/调研 | D2: 阅读MemSlides论文与代码仓库，梳理generate/revise/template-induct三段式流程与分层记忆设计，产出调研笔记 | E2: 共同 | F2: 共同 | G2: P1 | H2: 4 | J2: 产出调研笔记文档，团队能讲清MemSlides架构与本项目差异 | K2: 已完成 | L2: =项目概览!$B$11+(B2-1)*7 -> 46209 | M2: =L2+6 -> 46215
A3: T1.2 | B3: 1 | C3: 前期准备/调研 | D3: 搭建开发环境：Python/python-pptx/matplotlib/pandas/LLM API配置，跑通MemSlides smoke_minimal示例 | E3: 共同 | F3: 共同 | G3: P0 | H3: 4 | J3: 环境搭建成功，smoke test通过截图/日志 | K3: 已完成 | L3: =项目概览!$B$11+(B3-1)*7 -> 46209 | M3: =L3+6 -> 46215
A4: T1.3 | B4: 1 | C4: 前期准备/调研 | D4: 收集5-8份样例研报文本(含markdown)，覆盖不同行业，整理为测试数据集目录 | E4: 学生A | F4: 学生B | G4: P1 | H4: 4 | I4: T1.2 | J4: 测试数据集v0入库，含来源说明 | K4: 已完成 | L4: =项目概览!$B$11+(B4-1)*7 -> 46209 | M4: =L4+6 -> 46215
A5: T1.4 | B5: 1 | C5: 前期准备/调研 | D5: 设计/收集1-2套固定PPT模板风格(母版/配色/字体/占位符)，用python-pptx读取模板结构 | E5: 学生B | F5: 学生A | G5: P1 | H5: 4 | I5: T1.2 | J5: 模板文件+占位符结构说明文档 | K5: 已完成 | L5: =项目概览!$B$11+(B5-1)*7 -> 46209 | M5: =L5+6 -> 46215
A6: T1.5 | B6: 1 | C6: 前期准备/调研 | D6: 与导师确认验收标准(rubric)和Demo形式，整理项目章程 | E6: 共同 | F6: 共同 | G6: P0 | H6: 2 | J6: 项目章程文档定稿，导师确认 | K6: 未开始 | L6: =项目概览!$B$11+(B6-1)*7 -> 46209 | M6: =L6+6 -> 46215
A7: T2.1 | B7: 2 | C7: 内容结构化 | D7: 设计“大纲JSON”schema（幻灯片标题/要点/原文引用等字段） | E7: 学生A | F7: 学生B | G7: P0 | H7: 3 | I7: T1.5 | J7: schema文档定稿并评审通过 | K7: 未开始 | L7: =项目概览!$B$11+(B7-1)*7 -> 46216 | M7: =L7+6 -> 46222
A8: T2.2 | B8: 2 | C8: 内容结构化 | D8: 实现markdown/纯文本解析器：识别标题层级/段落/列表/已有markdown表格 | E8: 学生A | G8: P0 | H8: 5 | I8: T2.1 | J8: 解析器单测通过，覆盖3种以上格式样例 | K8: 未开始 | L8: =项目概览!$B$11+(B8-1)*7 -> 46216 | M8: =L8+6 -> 46222
A9: T2.3 | B9: 2 | C9: 内容结构化 | D9: 用LLM few-shot将解析结果切分为幻灯片大纲(公司概况/核心逻辑/财务预测/估值与风险等)，输出结构化JSON | E9: 学生A | G9: P0 | H9: 6 | I9: T2.2 | J9: 1份样例研报生成的大纲JSON人工评审通过 | K9: 未开始 | L9: =项目概览!$B$11+(B9-1)*7 -> 46216 | M9: =L9+6 -> 46222
A10: T2.4 | B10: 2 | C10: 排版引擎 | D10: 实现“大纲JSON→纯文本PPT”最小可行渲染器(标题页+要点页) | E10: 学生B | G10: P0 | H10: 6 | I10: T1.4 | J10: 可将大纲JSON渲染为基础PPT，无崩溃 | K10: 未开始 | L10: =项目概览!$B$11+(B10-1)*7 -> 46216 | M10: =L10+6 -> 46222
A11: T2.5 | B11: 2 | C11: 排版引擎 | D11: 研究MemSlides template induct思路，设计本项目“固定模板+可复用版式映射表” | E11: 学生B | F11: 学生A | G11: P1 | H11: 4 | I11: T1.4 | J11: 版式映射表文档，覆盖至少4种页面类型 | K11: 未开始 | L11: =项目概览!$B$11+(B11-1)*7 -> 46216 | M11: =L11+6 -> 46222
A12: T2.6 | B12: 2 | C12: 全流程集成 | D12: 打通端到端最小链路：1份样例研报→大纲JSON→纯文本PPT，联调 | E12: 共同 | F12: 共同 | G12: P0 | H12: 3 | I12: T2.3,T2.4 | J12: 端到端最小demo跑通并演示 | K12: 未开始 | L12: =项目概览!$B$11+(B12-1)*7 -> 46216 | M12: =L12+6 -> 46222
A13: T3.1 | B13: 3 | C13: 可视化定位与抽取 | D13: 设计可视化候选内容判定规则：关键词(同比/环比/增长率/毛利率/CAGR等)+数字正则初筛 | E13: 学生A | G13: P0 | H13: 3 | I13: T2.6 | J13: 规则文档+初筛脚本，在样例上召回率初评 | K13: 未开始 | L13: =项目概览!$B$11+(B13-1)*7 -> 46223 | M13: =L13+6 -> 46229
A14: T3.2 | B14: 3 | C14: 可视化定位与抽取 | D14: 设计结构化提取schema{类型,标题,单位,分类轴,系列数据,来源片段}，用LLM做结构化抽取 | E14: 学生A | G14: P0 | H14: 6 | I14: T3.1 | J14: 抽取脚本可输出符合schema的JSON | K14: 未开始 | L14: =项目概览!$B$11+(B14-1)*7 -> 46223 | M14: =L14+6 -> 46229
A15: T3.3 | B15: 3 | C15: 可视化定位与抽取 | D15: 人工标注20-30段测试文本的可视化点作为评估集，计算抽取准确率/召回率 | E15: 学生A | F15: 学生B | G15: P1 | H15: 4 | I15: T3.2 | J15: 评估报告(准确率/召回率数值) | K15: 未开始 | L15: =项目概览!$B$11+(B15-1)*7 -> 46223 | M15: =L15+6 -> 46229
A16: T3.4 | B16: 3 | C16: 可视化渲染 | D16: 实现图表渲染模块：结构化数据→bar/line/pie图片，配色与模板统一 | E16: 学生B | G16: P0 | H16: 6 | I16: T1.4 | J16: 图表渲染函数，3种图表类型样例图 | K16: 未开始 | L16: =项目概览!$B$11+(B16-1)*7 -> 46223 | M16: =L16+6 -> 46229
A17: T3.5 | B17: 3 | C17: 可视化渲染 | D17: 实现表格渲染模块：结构化数据→python-pptx原生表格，样式统一 | E17: 学生B | G17: P0 | H17: 4 | I17: T1.4 | J17: 表格渲染函数，样例表格截图 | K17: 未开始 | L17: =项目概览!$B$11+(B17-1)*7 -> 46223 | M17: =L17+6 -> 46229
A18: T3.6 | B18: 3 | C18: 全流程集成 | D18: 联调：抽取结果→图表/表格生成，跑通2-3个研报片段，人工核对数值准确性 | E18: 共同 | F18: 共同 | G18: P0 | H18: 3 | I18: T3.3,T3.4,T3.5 | J18: 图表数值与原文核对无误 | K18: 未开始 | L18: =项目概览!$B$11+(B18-1)*7 -> 46223 | M18: =L18+6 -> 46229
A19: T3.7 | B19: 3 | C19: 全流程集成 | D19: 合并结构化/抽取/可视化模块为单一Pipeline，定义模块间接口(函数/CLI) | E19: 共同 | F19: 共同 | G19: P0 | H19: 5 | I19: T3.6 | J19: 单命令跑通完整pipeline(首次全量打通) | K19: 未开始 | L19: =项目概览!$B$11+(B19-1)*7 -> 46223 | M19: =L19+6 -> 46229
A20: T4.1 | B20: 4 | C20: 排版引擎 | D20: 版式规则：根据内容类型自动选layout，处理文字溢出/图片过大问题 | E20: 学生B | G20: P0 | H20: 6 | I20: T3.7 | J20: 5份样例研报生成PPT无明显溢出/遮挡 | K20: 未开始 | L20: =项目概览!$B$11+(B20-1)*7 -> 46230 | M20: =L20+6 -> 46236
A21: T4.2 | B21: 4 | C21: 内容结构化 | D21: 补充非数值章节(投资建议/风险提示等)排版为要点页/结论页 | E21: 学生A | G21: P1 | H21: 3 | I21: T3.7 | J21: 非数值章节均有对应幻灯片 | K21: 未开始 | L21: =项目概览!$B$11+(B21-1)*7 -> 46230 | M21: =L21+6 -> 46236
A22: T4.3 | B22: 4 | C22: 测试与评估 | D22: 在全部样例研报上跑通端到端生成，记录并清理问题清单(bug/badcase)；向导师展示v1.0收集反馈 | E22: 共同 | F22: 共同 | G22: P0 | H22: 4 | I22: T4.1,T4.2 | J22: 问题清单中P0/P1项全部关闭，导师确认可交付 | K22: 未开始 | L22: =项目概览!$B$11+(B22-1)*7 -> 46230 | M22: =L22+6 -> 46236
A23: T4.4 | B23: 4 | C23: 测试与评估 | D23: 编写关键模块最小单元测试(pytest：解析器/抽取器/渲染器各1-2个用例) | E23: 共同 | F23: 共同 | G23: P1 | H23: 3 | I23: T4.3 | J23: 核心模块有单测，可一键运行 | K23: 未开始 | L23: =项目概览!$B$11+(B23-1)*7 -> 46230 | M23: =L23+6 -> 46236
A24: T4.5 | B24: 4 | C24: 测试与评估 | D24: 量化评估：数值准确性/版式合规率/生成成功率，汇总为评估表 | E24: 共同 | F24: 共同 | G24: P0 | H24: 3 | I24: T4.3 | J24: 评估报告含以上三项量化指标 | K24: 未开始 | L24: =项目概览!$B$11+(B24-1)*7 -> 46230 | M24: =L24+6 -> 46236
A25: T4.6 | B25: 4 | C25: 文档与交付 | D25: 代码整理、注释、README、环境搭建文档 | E25: 共同 | F25: 共同 | G25: P0 | H25: 3 | I25: T4.3 | J25: README可让新人独立跑通pipeline | K25: 未开始 | L25: =项目概览!$B$11+(B25-1)*7 -> 46230 | M25: =L25+6 -> 46236
A26: T4.7 | B26: 4 | C26: 文档与交付 | D26: 撰写项目总结报告(架构/方法/评估结果/与MemSlides对比/局限与未来工作) | E26: 共同 | F26: 共同 | G26: P0 | H26: 4 | I26: T4.5 | J26: 总结报告定稿 | K26: 未开始 | L26: =项目概览!$B$11+(B26-1)*7 -> 46230 | M26: =L26+6 -> 46236
A27: T4.8 | B27: 4 | C27: 文档与交付 | D27: 制作结项汇报PPT并向导师/团队展示(可尝试用自研工具生成) | E27: 共同 | F27: 共同 | G27: P0 | H27: 3 | I27: T4.6,T4.7 | J27: 汇报完成，获得导师验收签字 | K27: 未开始 | L27: =项目概览!$B$11+(B27-1)*7 -> 46230 | M27: =L27+6 -> 46236
A28: T4.9 | B28: 4 | C28: 项目管理 | D28: 代码/文档最终整理归档，更新Excel任务表至100%完成 | E28: 共同 | F28: 共同 | G28: P1 | H28: 1 | I28: T4.8 | J28: 任务跟踪表所有任务状态为“已完成” | K28: 未开始 | L28: =项目概览!$B$11+(B28-1)*7 -> 46230 | M28: =L28+6 -> 46236
A30: 可选/加分任务（不计入4周主线关键路径，进度超前或结项后可挑战）
A31: OPT1 | C31: 可视化定位与抽取(加强) | D31: 优化图表类型选择启发式规则(时间序列→折线/占比→饼图/对比→柱状图) | E31: 学生A | G31: P3 | H31: 4 | I31: T4.5 | J31: 图表类型选择准确率有量化提升 | K31: 未开始
A32: OPT2 | C32: 可视化渲染(加强) | D32: 增加可视化类型：同比/环比双轴图、图表+表格混合页 | E32: 学生B | G32: P3 | H32: 4 | I32: T4.5 | J32: 新增至少2种可视化样式并入库 | K32: 未开始
A33: OPT3 | C33: 进阶(可选) | D33: 参考MemSlides局部修订思路，实现“指定幻灯片局部重新生成”最小功能 | E33: 共同 | G33: P3 | H33: 6 | I33: OPT1,OPT2 | J33: 可对单页内容发起局部重生成且不影响其他页 | K33: 未开始
C35: 汇总(4周主线)： | D35: 已完成任务数 / 总任务数 | J35: =COUNTIF(K2:K28,"已完成")&" / "&27 -> 4 / 27
D36: 总预计工时(h，主线) | J36: =SUM(H2:H28) -> 106

Sheet 验收标准
A1: 维度 | B1: 描述 | C1: 合格标准 | D1: 优秀标准
A2: 功能完整性 | B2: 输入任意研报文本能生成完整PPT | C2: 对全部样例研报生成不崩溃，输出.pptx可正常打开 | D2: 支持markdown表格/多级标题等多样格式的鲁棒解析
A3: 可视化定位准确率 | B3: 数值信息识别为图表/表格候选的准确率与召回率 | C3: 标注评估集上准确率与召回率均≥70% | D3: 准确率与召回率均≥85%，且图表类型选择合理
A4: 数值准确性 | B4: 图表/表格中的数值与原文一致，无幻觉 | C4: 抽样核对无数值错误率超过5% | D4: 抽样核对数值零错误
A5: 版式质量 | B5: 幻灯片无文字溢出/图片遮挡/风格不统一 | C5: ≥90%幻灯片版式正常 | D5: 100%幻灯片版式正常，视觉统一美观
A6: 风格一致性 | B6: 全篇PPT使用统一的固定模板风格 | C6: 所有幻灯片使用同一模板/配色/字体 | D6: 模板可配置切换，且切换后依然保持一致性
A7: 工程质量 | B7: 代码可维护、可复现 | C7: 有README，环境可一键搭建，关键模块有单测 | D7: 有CI自动化测试，模块化清晰，具备可扩展性(如支持局部修订)
A8: 交付完整性 | B8: 文档与Demo齐全 | C8: 总结报告+代码仓库+Demo PPT | D8: 含评估报告与未来工作展望，团队可清晰讲解架构

Sheet 风险与问题跟踪
A1: 编号 | B1: 类别 | C1: 描述 | D1: 影响 | E1: 可能性 | F1: 应对措施 | G1: 负责人 | H1: 状态 | I1: 更新日期
A2: R1 | B2: 技术风险 | C2: LLM数值抽取产生“幻觉”，图表数值与原文不符 | D2: 生成结果不可信，需人工核对成本高 | E2: 中 | F2: 抽取后强制与原文正则/字符串核对；不一致则标记待人工确认 | G2: 学生A | H2: 未开始
A3: R2 | B3: 技术风险 | C3: PPT自动排版导致文字溢出或图片遮挡 | D3: 输出视觉质量差，影响验收 | E3: 中 | F3: 预留自动缩放/截断规则，设计多套版式模板兜底 | G3: 学生B | H3: 未开始
A4: R3 | B4: 进度风险 | C4: 本科生每周可投入时间有限，4周任务量偏紧(平均约25-30h/周，两人合计) | D4: 4周内无法完成核心流程 | E4: 中 | F4: 每周五对照“任务跟踪表”校准进度；单项任务延期就地把“计划周次”改为5+顺延，不重排其余任务，最长不超过8周 | G4: 共同 | H4: 未开始
A5: R4 | B5: 数据风险 | C5: 样例研报数据量不足，覆盖行业/格式不全 | D5: 模型泛化能力评估不充分 | E5: 低 | F5: 第1周和第6周两次集中收集/扩充测试数据集 | G5: 学生A | H5: 未开始
A6: R5 | B6: 协作风险 | C6: 两人模块接口定义不一致导致联调困难 | D6: 集成阶段返工 | E6: 中 | F6: Week2/Week4集成前先对齐JSON schema与函数签名文档 | G6: 共同 | H6: 未开始

Sheet 测试数据集清单
A1: 编号 | B1: 研报名称/公司 | C1: 所属行业 | D1: 来源 | E1: 字数(约) | F1: 含Markdown表格 | G1: 标注状态 | H1: 备注
A2: 1 | B2: 翰博高新（301321） | C2: 光学光电子 | D2: 第一周/测试研报/光学光电子.pdf | E2: 5300 | F2: 是 | G2: 已转换为Markdown | H2: 买入；2026-07-07；5页；Markdown：光学光电子.md
A3: 2 | B3: 水泥 | C3: 水泥 | D3: 第一周/测试研报/水泥.pdf | E3: 4900 | F3: 是 | G3: 已转换为Markdown | H3: ；2026-07-10；4页；Markdown：水泥.md
A4: 3 | B4: 三祥科技（920195） | C4: 汽车零部件 | D4: 第一周/测试研报/汽车零部件.pdf | E4: 14400 | F4: 是 | G4: 已转换为Markdown | H4: 买入；2026-07-11；23页；Markdown：汽车零部件.md
A5: 4 | B5: 浙数文化（600633） | C5: 游戏Ⅱ | D5: 第一周/测试研报/游戏Ⅱ.pdf | E5: 23600 | F5: 是 | G5: 已转换为Markdown | H5: 买入；2026-07-08；28页；Markdown：游戏Ⅱ.md
A6: 5 | B6: 酷特智能（300840） | C6: 纺织家居 | D6: 第一周/测试研报/纺织家居.pdf | E6: 3400 | F6: 是 | G6: 已转换为Markdown | H6: 买入；2026-07-10；5页；Markdown：纺织家居.md
A7: 6 | B7: 大族激光（002008） | C7: 自动化设备 | D7: 第一周/测试研报/自动化设备.pdf | E7: 4000 | F7: 是 | G7: 已转换为Markdown | H7: 买入；2026-07-10；3页；Markdown：自动化设备.md
A8: 7 | B8: 中远海能（600026） | C8: 航运港口 | D8: 第一周/测试研报/航运港口.pdf | E8: 4700 | F8: 是 | G8: 已转换为Markdown | H8: 买入；2026-07-11；3页；Markdown：航运港口.md
A9: 8 | B9: 中信证券（600030） | C9: 证券Ⅱ | D9: 第一周/测试研报/证券Ⅱ.pdf | E9: 4400 | F9: 是 | G9: 已转换为Markdown | H9: 买入；2026-07-10；5页；Markdown：证券Ⅱ.md
